gradio_igv/__init__.py
gradio_igv/data_types.py
gradio_igv/features.py
gradio_igv/igv.py
gradio_igv/igv.pyi
gradio_igv/templates/component/index.js
gradio_igv/templates/component/style.css
gradio_igv/templates/example/index.js
gradio_igv/templates/example/style.css
gradio_igv-0.1.0.dist-info/METADATA
gradio_igv-0.1.0.dist-info/WHEEL
gradio_igv-0.1.0.dist-info/licenses/LICENSE
gradio_igv-0.1.0.dist-info/RECORD
