Metadata-Version: 2.4
Name: gradio_igv
Version: 0.1.0
Summary: Embed IGV.js in your app to visualize genomics data.
Author-email: Ricky Magner <rmagner@broadinstitute.org>
License-Expression: BSD-3-Clause
License-File: LICENSE
Keywords: DNA,IGV,genomics,gradio-custom-component,gradio-template-Fallback
Classifier: Development Status :: 3 - Alpha
Classifier: Operating System :: OS Independent
Classifier: Programming Language :: Python :: 3
Classifier: Programming Language :: Python :: 3 :: Only
Classifier: Programming Language :: Python :: 3.8
Classifier: Programming Language :: Python :: 3.9
Classifier: Programming Language :: Python :: 3.10
Classifier: Programming Language :: Python :: 3.11
Classifier: Topic :: Scientific/Engineering
Classifier: Topic :: Scientific/Engineering :: Artificial Intelligence
Classifier: Topic :: Scientific/Engineering :: Visualization
Requires-Python: >=3.10
Requires-Dist: gradio<6.0,>=4.0
Requires-Dist: pysam>=0.20.0
Provides-Extra: dev
Requires-Dist: build; extra == 'dev'
Requires-Dist: twine; extra == 'dev'
